{
  "Order": [
    {
      "address": "Số 2 Hoa Lư - Quận Hai Bà Trưng - Hà Nội",
      "checked": true,
      "comment": "no",
      "date": "2023-06-15",
      "email": "cm@gmail.com",
      "guests": "2",
      "hour": "10",
      "id": 1,
      "minutes": "3",
      "name": "Huy",
      "phone": "0947589566"
    },
    {
      "address": "Biệt Thự D17, Ngõ 76 Nguyễn Phong Sắc",
      "checked": true,
      "comment": "có trẻ em",
      "date": "2023-06-15",
      "email": "thaott@gmail.com",
      "guests": "5",
      "hour": "8",
      "id": 2,
      "minutes": "10",
      "name": "thao",
      "phone": "0923454131"
    },
    null,
    {
      "address": "02 Đặng Dung Ba Đình",
      "checked": true,
      "comment": "ok",
      "date": "2023-06-15",
      "email": "hoangg@gmail.com",
      "guests": "3",
      "hour": "10",
      "id": 4,
      "minutes": "10",
      "name": "Hoàng",
      "phone": "0963645566"
    }
  ],
  "cartlist": [
    {
      "contact-name": "hungw",
      "contact-email": "ad@gmail.com",
      "contact-hour": "8",
      "contact-message": "doen",
      "contact-minute": "1",
      
      "contact-phone": "094-155-4567",
      "contact-time": "2023-06-15"
    }
  ],
  "categories": [
    {
      "id": 1,
      "name": "TẤT CẢ"
    },
    {
      "id": 2,
      "name": "BÒ NHẬP KHẨU"
    },
    {
      "id": 3,
      "name": "BÒ KOBE"
    },
    {
      "id": 4,
      "name": "COMBO"
    },
    {
      "id": 5,
      "name": "SALAT"
    },
    {
      "id": 6,
      "name": "KHAI VỊ"
    },
    {
      "id": 7,
      "name": "ĐẦU BẾP ĐẶC BIỆT"
    },
    {
      "id": 8,
      "name": "HOT"
    },
    {
      "id": 9,
      "name": "CƠM-MỲ"
    },
    {
      "id": 10,
      "name": "TRÁNG MIỆNG"
    },
    {
      "id": 11,
      "name": "ĐỒ UỐNG"
    },
    {
      "id": 12,
      "name": "RƯỢU"
    }
  ],
  "demo": {
    "-NXnuUlDxlpeSnhX3IXx": {
      "12": {
        "id": 13,
        "name": "ĐỒ NHÚNG LẨU"
      }
    }
  },
  "order": [
    {
      "address": "102 Thái Thịnh ",
      "checked": true,
      "comment": "done",
      "date": "2023-06-15",
      "email": "huycc@gmail.com",
      "guests": "5",
      "hour": "10",
      "id": 1,
      "minutes": "7",
      "name": "Huy",
      "phone": "0923451234"
    }
  ],
  "productsCate": [
    {
      "describe": "450Gr thịt bò + 1gr Muối tinh +1 gr Tiêu Xanh ",
      "id": 34,
      "img": "../images/product/combo1.jpg",
      "name": "TẤT CẢ",
      "nameFood": "Steak Thịt Vai Wagyu (450Gr)",
      "price": 390000,
      "review": " 67 Đánh Giá Món Ăn",
      "reviewDemo": 4.5,
      "start": "01/01/2023"
    },
    {
      "id": 2,
      "describe": " thịt bò + 1gr Muối tinh +1 gr Tiêu Xanh ",
      "img": "../images/product/daubep.jpg",
      "name": "TẤT CẢ",
      "nameFood": "Đầu Bếp Carpaccio (Nhật Bản)",
      "price": 320000,
      "review": " 81 Đánh Giá Món Ăn",
      "reviewDemo": 4.8,
      "start": "03/01/2023"
    },
    {
      "id": 3,
      "describe": " thịt bò + 1gr Muối tinh +1 gr Tiêu Xanh + Dầu Oliu ",
      "img": "../images/product/combo2.jpg",
      "name": "TẤT CẢ",
      "nameFood": "Combo Bò Wagyu Đặc Biệt",
      "price": 720000,
      "review": " 80 Đánh Giá Món Ăn",
      "reviewDemo": 4,
      "start": "01/01/2023"
    },
    {
      "id": 4,
      "img": "../images/product/pas.jpg",
      "name": "TẤT CẢ",
      "nameFood": "Sushi Bò Tuyết Nướng (Thượng Hạng)",
      "price": 450000,
      "review": " 68 Đánh Giá Món Ăn",
      "reviewDemo": 5,
      "start": "01/01/2023"
    },
    {
      "id": 5,
      "describe": " thịt bò + 1gr Muối tinh +1 gr Tiêu Xanh + Dầu Oliu ",
      "img": "../images/product/macao.jpg",
      "name": "TẤT CẢ",
      "nameFood": "Bò Áp Chảo Macau (450gr) ",
      "price": 270000,
      "review": "23 Đánh Giá Món Ăn",
      "reviewDemo": 4.6,
      "start": "01/01/2023"
    },
    {
      "id": 6,
      "describe": " thịt bò + 1gr Muối tinh +1 gr Tiêu Xanh + Dầu Oliu ",
      "img": "../images/product/bbq.jpg",
      "name": "TẤT CẢ",
      "nameFood": "Sườn Bò Nướng Sốt BBQ (500gr)",
      "price": 560000,
      "review": " 76 Đánh Giá Món Ăn",
      "reviewDemo": 5,
      "start": "01/01/2023"
    },
    {
      "id": 7,
      "describe": " thịt bò + 1gr Muối tinh +1 gr Tiêu Xanh + Dầu Oliu ",
      "img": "../images/product/bbt.jpg",
      "name": "TẤT CẢ",
      "nameFood": "Bò Bít Tết (Beef Steak) 'Sale 30%'",
      "price": 250000,
      "review": "45 Đánh Giá Món Ăn",
      "reviewDemo": 4.1,
      "start": "01/01/2023"
    },
    {
      "id": 8,
      "describe": " thịt bò + 1gr Muối tinh +1 gr Tiêu Xanh + Dầu Oliu ",
      "img": "../images/product/hinh1a.jpg",
      "name": "TẤT CẢ",
      "nameFood": "Steak Thịt Vai Wagyu (370gr)",
      "price": 540000,
      "review": "89 Đánh Giá Món Ăn",
      "reviewDemo": 4.5,
      "start": "01/01/2023"
    },
    {
      "id": 9,
      "describe": " thịt bò + 1gr Muối tinh +1 gr Tiêu Xanh + Dầu Oliu ",
      "img": "../images/product/thanbo.jpg",
      "name": "TẤT CẢ",
      "nameFood": "Steak Thăn Bò (450Gr) 'Sale 30%'",
      "price": 820000,
      "review": "98 Đánh Giá Món Ăn",
      "reviewDemo": 4.7,
      "start": "01/01/2023"
    },
    {
      "id": 10,
      "describe": " thịt bò + 1gr Muối tinh +1 gr Tiêu Xanh + Dầu Oliu ",
      "img": "../images/product/bbq2.jpg",
      "name": "BÒ NHẬP KHẨU",
      "nameFood": "Bò Bít Tết (Châu Âu) 'Sale 15%'",
      "price": 650000,
      "review": "90 Đánh Giá Món Ăn",
      "reviewDemo": 4.8,
      "start": "01/01/2023"
    },
    {
      "id": 11,
      "describe": " thịt bò + 1gr Muối tinh +1 gr Tiêu Xanh + Dầu Oliu ",
      "img": "../images/product/bbq3.jpg",
      "name": "BÒ NHẬP KHẨU",
      "nameFood": "Bò Nướng Tảng (350gr) 'Sale 30%'",
      "price": 420000,
      "review": "54 Đánh Giá Món Ăn",
      "reviewDemo": 4.9,
      "start": "01/01/2023"
    },
    {
      "id": 12,
      "describe": " thịt bò + 1gr Muối tinh +1 gr Tiêu Xanh + Dầu Oliu ",
      "img": "../images/product/hot.jpg",
      "name": "HOT",
      "nameFood": "Bò Nướng BBQ (Nướng Than Hoa)",
      "price": 340000,
      "review": " 56 Đánh Giá Món Ăn",
      "reviewDemo": 4.5,
      "start": "01/01/2023"
    },
    {
      "id": 13,
      "describe": " thịt bò + 1gr Muối tinh +1 gr Tiêu Xanh + Dầu Oliu ",
      "img": "../images/product/hot1.jpg",
      "name": "HOT",
      "nameFood": "Bò Nướng BBQ + Sốt Thái (450gr)",
      "price": 340000,
      "review": " 26 Đánh Giá Món Ăn",
      "reviewDemo": 4.1,
      "start": "01/01/2023"
    },
    {
      "id": 14,
      "describe": " thịt bò + 1gr Muối tinh +1 gr Tiêu Xanh + Dầu Oliu ",
      "img": "../images/product/hot2.jpg",
      "name": "HOT",
      "nameFood": "Bò Hoàng Gia (Nhập Khẩu Anh Quốc)",
      "price": 340000,
      "review": " 56 Đánh Giá Món Ăn",
      "reviewDemo": 4.5,
      "start": "01/01/2023"
    },
    {
      "id": 15,
      "describe": " thịt bò + 1gr Muối tinh +1 gr Tiêu Xanh + Dầu Oliu ",
      "img": "../images/product/hot3.jpg",
      "name": "HOT",
      "nameFood": "KING BBQ (Món Bắc Âu) 'Sale 15%'",
      "price": 340000,
      "review": " 56 Đánh Giá Món Ăn",
      "reviewDemo": 4.5,
      "start": "01/01/2023"
    },
    {
      "id": 16,
      "describe": " thịt bò + 1gr Muối tinh +1 gr Tiêu Xanh + Dầu Oliu ",
      "img": "../images/product/bbq.jpg",
      "name": "HOT",
      "nameFood": "Bò Mỹ Áp Chảo Chín (350gr)'Sale 20%'",
      "price": 340000,
      "review": " 56 Đánh Giá Món Ăn",
      "reviewDemo": 4.5,
      "start": "01/01/2023"
    },
    {
      "id": 17,
      "describe": " thịt bò + 1gr Muối tinh +1 gr Tiêu Xanh + Dầu Oliu ",
      "img": "../images/product/hot4.jpg",
      "name": "HOT",
      "nameFood": "Sườn Bò Nướng BBQ (450gr) 'Sale 5%'",
      "price": 340000,
      "review": " 56 Đánh Giá Món Ăn",
      "reviewDemo": 4.5,
      "start": "01/01/2023"
    },
    {
      "id": 18,
      "img": "../images/product/bbq5.jpg",
      "name": "BÒ NHẬP KHẨU",
      "nameFood": "Thăn Bò Nướng Đá Núi Lửa",
      "price": 350000,
      "review": "76 Đánh Giá Món Ăn",
      "reviewDemo": 4.9,
      "start": "01/01/2023"
    },
    {
      "id": 19,
      "describe": " thịt bò + 1gr Muối tinh +1 gr Tiêu Xanh + Dầu Oliu ",
      "img": "../images/product/chef.jpg",
      "name": "TẤT CẢ",
      "nameFood": "Bò Sốt Tiêu Đen (250gr) 'Sale 30%'",
      "price": 390000,
      "review": "Đánh Giá Món Ăn1",
      "reviewDemo": 20,
      "start": "01/01/2023"
    },
    {
      "id": 20,
      "img": "../images/product/thanbo.jpg",
      "name": "BÒ NHẬP KHẨU",
      "nameFood": "Steak Thịt Thăn Bò (450Gr)",
      "price": 820000,
      "review": "98 Đánh Giá Món Ăn",
      "reviewDemo": 4.7,
      "start": "01/01/2023"
    },
    {
      "id": 21,
      "img": "../images/product/bbq.jpg",
      "name": "BÒ NHẬP KHẨU",
      "nameFood": "Sườn Bò Nướng Sốt BBQ",
      "price": 560000,
      "review": " 76 Đánh Giá Món Ăn",
      "reviewDemo": 5,
      "start": "01/01/2023"
    },
   
    {
      "id": 23,
      "img": "../images/product/pas.jpg",
      "name": "BÒ KOBE",
      "nameFood": "Sushi Bò Tuyết Nướng (Thượng Hạng)",
      "price": 450000,
      "review": " 68 Đánh Giá Món Ăn",
      "reviewDemo": 5,
      "start": "01/01/2023"
    },
    {
      "id": 24,
      "img": "../images/product/bbq4.jpg",
      "name": "BÒ KOBE",
      "nameFood": "Bò Tái + Sốt Hàn (450gr) 'Sale 18%'",
      "price": 340000,
      "review": " 56 Đánh Giá Món Ăn",
      "reviewDemo": 4.5,
      "start": "01/01/2023"
    },
    {
      "id": 25,
      "img": "../images/product/hinh2.2.jpg",
      "name": "BÒ KOBE",
      "nameFood": "Steak Thịt Thăn Wagyu (450Gr)",
      "price": 390000,
      "review": " 67 Đánh Giá Món Ăn",
      "reviewDemo": 4.5,
      "start": "01/01/2023"
    },
    {
      "id": 26,
      "img": "../images/product/bbq3.jpg",
      "name": "BÒ KOBE",
      "nameFood": "Bò Nướng Tảng + Rau Củ (330gr)",
      "price": 420000,
      "review": "54 Đánh Giá Món Ăn",
      "reviewDemo": 4.9,
      "start": "01/01/2023"
    },
    {
      "id": 27,
      "img": "../images/product/combo1.jpg",
      "name": "COMBO",
      "nameFood": "Combo Lớn (Steak Bụng Bò, Lưỡi Bò, Mông Trên, Thịt Xông Khói, Xúc Xích)",
      "price": 990000,
      "review": " 77 Đánh Giá Món Ăn",
      "reviewDemo": 4.8,
      "start": "03/01/2023"
    },
    {
      "id": 28,
      "img": "../images/product/combo2.jpg",
      "name": "COMBO",
      "nameFood": "Combo Bò Wagyu Đặc Biệt (Steak Thăn Nội, Steak Thăn Ngoại, Steak Mông Trên)",
      "price": 820000,
      "review": "28 Đánh Giá Món Ăn",
      "reviewDemo": 4.2,
      "start": "01/01/2023"
    },
    {
      "id": 29,
      "img": "../images/product/combo3.jpg",
      "name": "COMBO",
      "nameFood": "Combo Bò Wagyu 5 Loại (Steak Nạc Vai, Mông Trên, Mông Đùi, Thịt Sườn, Mông Giữa)",
      "price": 820000,
      "review": "9 Đánh Giá Món Ăn",
      "reviewDemo": 4.3,
      "start": "01/01/2023"
    },
    {
      "id": 30,
      "img": "../images/product/combo5.jpg",
      "name": "COMBO",
      "nameFood": "Combo 3 Loại (Steak Bụng Bò, Lưỡi Bò, Mông Trên)",
      "price": 820000,
      "review": "92 Đánh Giá Món Ăn",
      "reviewDemo": 4.7,
      "start": "01/01/2023"
    },
    {
      "id": 31,
      "img": "../images/product/combo4.jpg",
      "name": "COMBO",
      "nameFood": "Combo Bò Wagyu 3 Loại (Steak Nạc Vai, Mông Trên, Mông Đùi)",
      "price": 820000,
      "review": "8 Đánh Giá Món Ăn",
      "reviewDemo": 4.8,
      "start": "01/01/2023"
    },
    {
      "id": 32,
      "img": "../images/product/combo2.jpg",
      "name": "COMBO",
      "nameFood": "Combo 3 Loại (Steak Bụng Bò, Lưỡi Bò, Mông Trên)",
      "price": 290000,
      "review": " 34 Đánh Giá Món Ăn",
      "reviewDemo": 4.9,
      "start": "03/01/2023"
    },
    {
      "id": 33,
      "img": "../images/product/salat2.jpg",
      "name": "SALAT",
      "nameFood": "Salad Cà Chua + Rau Củ 'Sale 20%' ",
      "price": 550000,
      "review": " 98 Đánh Giá Món Ăn",
      "reviewDemo": 4.1,
      "start": "03/01/2023"
    },
    {
      "id": 35,
      "img": "../images/product/salat3.jpg",
      "name": "SALAT",
      "nameFood": "Salat Hoa Quả Nhiệt Đới 'Sale 10%'",
      "price": 550000,
      "review": "76 Đánh Giá Món Ăn",
      "reviewDemo": 4.8,
      "start": "03/01/2023"
    },
   
    {
      "id": 36,
      "img": "../images/product/salat8.jpg",
      "name": "SALAT",
      "nameFood": " Salat Tôm Sú Tái Chanh 'Sale 15%'",
      "price": 550000,
      "review": "32 Đánh Giá Món Ăn",
      "reviewDemo": 4.7,
      "start": "03/01/2023"
    },
    {
      "id": 37,
      "img": "../images/product/salat9.jpg",
      "name": "SALAT",
      "nameFood": " Salat Trứng Cua Rong Biển",
      "price": 550000,
      "review": " 32 Đánh Giá Món Ăn",
      "reviewDemo": 4.2,
      "start": "03/01/2023"
    },
    {
      "id": 38,
      "img": "../images/product/salat4.jpg",
      "name": "SALAT",
      "nameFood": "Salat Ý (Trái Cây + Dầu Oliu) 'Sale 12%' ",
      "price": 550000,
      "review": " 90 Đánh Giá Món Ăn",
      "reviewDemo": 4.3,
      "start": "03/01/2023"
    },
    {
      "id": 39,
      "img": "../images/product/khaivi.jpg",
      "name": "KHAI VỊ",
      "nameFood": "Set Ham Tươi & Phô Mai",
      "price": 180000,
      "review": "74 Đánh Giá Món Ăn",
      "reviewDemo": 4.8,
      "start": "03/01/2023"
    },
    {
      "id": 40,
      "img": "../images/product/khaivi2.jpg",
      "name": "KHAI VỊ",
      "nameFood": "Gỏi Củ Hủ Dừa (Tôm Sú + Dừa)",
      "price": 180000,
      "review": " 65 Đánh Giá Món Ăn",
      "reviewDemo": 4.2,
      "start": "03/01/2023"
    },
    {
      "id": 41,
      "img": "../images/product/khaivi3.jpg",
      "name": "KHAI VỊ",
      "nameFood": " Gỏi Ngó Sen Tôm Thịt 'Sale 20%'",
      "price": 180000,
      "review": "Đánh Giá Món Ăn3",
      "reviewDemo": 4.7,
      "start": "03/01/2023"
    },
    {
      "id": 42,
      "img": "../images/product/khaivi4.jpg",
      "name": "KHAI VỊ",
      "nameFood": "Gỏi Bò Mè Bóp Thấu 'Sale 10%'",
      "price": 180000,
      "review": "68 Đánh Giá Món Ăn",
      "reviewDemo": 4.8,
      "start": "03/01/2023"
    },
    {
      "id": 43,
      "img": "../images/product/khaivi5.jpg",
      "name": "KHAI VỊ",
      "nameFood": " Gỏi Tiến Vua Tôm Thịt + Bánh Phồng",
      "price": 180000,
      "review": "11 Đánh Giá Món Ăn",
      "reviewDemo": 4.5,
      "start": "03/01/2023"
    },
    {
      "id": 44,
      "img": "../images/product/khaivi6.jpg",
      "name": "KHAI VỊ",
      "nameFood": "Gỏi Miến Trộn Tôm Thịt 'Sale 20%'",
      "price": 180000,
      "review": " 54 Đánh Giá Món Ăn",
      "reviewDemo": 4.1,
      "start": "03/01/2023"
    },
    
    {
      "id": 46,
      "img": "../images/product/daubep.jpg",
      "name": "ĐẦU BẾP ĐẶC BIỆT",
      "nameFood": "Đầu Bếp Carpaccio (Nhật Bản)",
      "price": 320000,
      "review": " 81 Đánh Giá Món Ăn",
      "reviewDemo": 4.8,
      "start": "03/01/2023"
    },
    {
      "id": 47,
      "img": "../images/product/hinh1.jpg",
      "name": "HOT",
      "nameFood": "Bò Bằm Sốt Tiêu & Kem (420gr)",
      "price": 320000,
      "review": " 64 Đánh Giá Món Ăn",
      "reviewDemo": "4.8",
      "start": "03/01/2023"
    },
    {
      "id": 48,
      "img": "../images/product/susi.jpg",
      "name": "CƠM-MỲ",
      "nameFood": "SUSHI Quấn Thăn Bò 'Sale 20%'",
      "price": 150000,
      "review": "11 Đánh Giá Món Ăn",
      "reviewDemo": 4.1,
      "start": "03/01/2023"
    },
    {
      "id": 49,
      "img": "../images/product/susi1.jpg",
      "name": "CƠM-MỲ",
      "nameFood": "Cơm Cuộn Bò Mỹ + Sốt Tiêu Đen",
      "price": 50000,
      "review": "22 Đánh Giá Món Ăn",
      "reviewDemo": 4,
      "start": "03/01/2023"
    },
    {
      "id": 50,
      "img": "../images/product/susi2.jpg",
      "name": "CƠM-MỲ",
      "nameFood": "SUSHI ( Rong Biển + Xì Dầu Mù Tạp )",
      "price": 210000,
      "review": " 56 Đánh Giá Món Ăn",
      "reviewDemo": 4.8,
      "start": "03/01/2023"
    },
    {
      "id": 51,
      "img": "../images/product/my2.jpg",
      "name": "CƠM-MỲ",
      "nameFood": "Mì Spaghetti Bò Bằm (Sốt Cay)",
      "price": 150000,
      "review": " 65 Đánh Giá Món Ăn",
      "reviewDemo": 4.8,
      "start": "03/01/2023"
    },
    {
      "id": 52,
      "img": "../images/product/my3.jpg",
      "name": "CƠM-MỲ",
      "nameFood": "Mỳ Ống Ý ( Thịt Bò Băm + Mỳ Ống)",
      "price": 250000,
      "review": "89 Đánh Giá Món Ăn",
      "reviewDemo": 4.1,
      "start": "03/01/2023"
    },
    {
      "id": 53,
      "img": "../images/product/my1.jpg",
      "name": "CƠM-MỲ",
      "nameFood": "Mỳ Ống Trộn Cà Chua Bi Và Phô Mai",
      "price": 90000,
      "review": " 121 Đánh Giá Món Ăn",
      "reviewDemo": "4.8",
      "start": "03/01/2023"
    },
    {
      "id": 54,
      "describe": " Kem + Trái Cây Nhiệt Đới ",
      "img": "../images/product/traicay.jpg",
      "name": "TẤT CẢ",
      "nameFood": "Hoa Quả Tráng Miệng - Kem Trái Cây",
      "price": 110000,
      "review": "96 Đánh Giá Món Ăn",
      "reviewDemo": 4.7,
      "start": "03/01/2023"
    },
    {
      "id": 55,
      "img": "../images/product/traicay2.jpg",
      "name": "TẤT CẢ",
      "nameFood": "Hoa Quả Tráng Miệng - Trái Cây Nhiệt Đới",
      "price": 150000,
      "review": "68 Đánh Giá Món Ăn",
      "reviewDemo": 4.8,
      "start": "03/01/2023"
    },
    {
      "id": 56,
      "img": "../images/product/traicay.jpg",
      "name": "TRÁNG MIỆNG",
      "nameFood": "Hoa Quả Tráng Miệng - Thố Kem Trái Cây",
      "price": 160000,
      "review": "Đánh Giá Món Ăn",
      "reviewDemo": 4.2,
      "start": "03/01/2023"
    },
    {
      "id": 57,
      "img": "../images/product/traicay1.jpg",
      "name": "TRÁNG MIỆNG",
      "nameFood": "Hoa Quả Tráng Miệng - Kem Hoa Quả",
      "price": 99,
      "review": "12 Đánh Giá Món Ăn",
      "reviewDemo": 4.3,
      "start": "03/01/2023"
    }
  ],
  "user": [
    {
      "email": "longdragon@gmail.com",
      "id": 1,
      "name": "admin",
      "password": 123456,
      "phone": "0123424571"
    },
    {
      "email": "hitle@gmail.com",
      "id": 2,
      "name": "karamel",
      "password": "654321",
      "phone": "0836765743"
    }
  ]
}